<?xml version="1.0" encoding="UTF-8" standalone="yes"?>
<instrumentRecording>
  <globalParameter>
    <audioFileName>\FS_Lick12_MN.wav</audioFileName>
    <instrument>EGUI</instrument>
    <instrumentModel>Fender Stratocaster</instrumentModel>
    <pickUpSetting>unknown</pickUpSetting>
    <instrumentTuning>40  45  50  55  59  64</instrumentTuning>
    <recordingDate>13-02-14</recordingDate>
    <recordingArtist>Christian Kehling</recordingArtist>
    <instrumentBodyMaterial>unknown</instrumentBodyMaterial>
    <instrumentStringMaterial>Steel</instrumentStringMaterial>
    <composer>Christian Kehling</composer>
  </globalParameter>
  <transcription>
    <event>
      <onsetSec>1.9447</onsetSec>
      <pitch>45</pitch>
      <offsetSec>2.4673</offsetSec>
      <excitationStyle>MU</excitationStyle>
      <expressionStyle>NO</expressionStyle>
      <fretNumber>0</fretNumber>
      <stringNumber>2</stringNumber>
      <modulationFrequency>0</modulationFrequency>
      <modulationFrequencyRange>0</modulationFrequencyRange>
    </event>
    <event>
      <onsetSec>2.2259</onsetSec>
      <pitch>52</pitch>
      <offsetSec>2.45</offsetSec>
      <excitationStyle>MU</excitationStyle>
      <expressionStyle>NO</expressionStyle>
      <fretNumber>2</fretNumber>
      <stringNumber>3</stringNumber>
      <modulationFrequency>0</modulationFrequency>
      <modulationFrequencyRange>0</modulationFrequencyRange>
    </event>
    <event>
      <onsetSec>2.4526</onsetSec>
      <pitch>59</pitch>
      <offsetSec>2.7111</offsetSec>
      <excitationStyle>MU</excitationStyle>
      <expressionStyle>NO</expressionStyle>
      <fretNumber>4</fretNumber>
      <stringNumber>4</stringNumber>
      <modulationFrequency>0</modulationFrequency>
      <modulationFrequencyRange>0</modulationFrequencyRange>
    </event>
    <event>
      <onsetSec>2.6957</onsetSec>
      <pitch>52</pitch>
      <offsetSec>2.9646</offsetSec>
      <excitationStyle>MU</excitationStyle>
      <expressionStyle>NO</expressionStyle>
      <fretNumber>2</fretNumber>
      <stringNumber>3</stringNumber>
      <modulationFrequency>0</modulationFrequency>
      <modulationFrequencyRange>0</modulationFrequencyRange>
    </event>
    <event>
      <onsetSec>2.9478</onsetSec>
      <pitch>64</pitch>
      <offsetSec>3.156</offsetSec>
      <excitationStyle>MU</excitationStyle>
      <expressionStyle>NO</expressionStyle>
      <fretNumber>0</fretNumber>
      <stringNumber>6</stringNumber>
      <modulationFrequency>0</modulationFrequency>
      <modulationFrequencyRange>0</modulationFrequencyRange>
    </event>
    <event>
      <onsetSec>3.2109</onsetSec>
      <pitch>59</pitch>
      <offsetSec>3.3707</offsetSec>
      <excitationStyle>MU</excitationStyle>
      <expressionStyle>NO</expressionStyle>
      <fretNumber>0</fretNumber>
      <stringNumber>5</stringNumber>
      <modulationFrequency>0</modulationFrequency>
      <modulationFrequencyRange>0</modulationFrequencyRange>
    </event>
    <event>
      <onsetSec>3.9329</onsetSec>
      <pitch>48</pitch>
      <offsetSec>4.4347</offsetSec>
      <excitationStyle>MU</excitationStyle>
      <expressionStyle>NO</expressionStyle>
      <fretNumber>3</fretNumber>
      <stringNumber>2</stringNumber>
      <modulationFrequency>0</modulationFrequency>
      <modulationFrequencyRange>0</modulationFrequencyRange>
    </event>
    <event>
      <onsetSec>4.1977</onsetSec>
      <pitch>52</pitch>
      <offsetSec>4.6381</offsetSec>
      <excitationStyle>MU</excitationStyle>
      <expressionStyle>NO</expressionStyle>
      <fretNumber>2</fretNumber>
      <stringNumber>3</stringNumber>
      <modulationFrequency>0</modulationFrequency>
      <modulationFrequencyRange>0</modulationFrequencyRange>
    </event>
    <event>
      <onsetSec>4.4172</onsetSec>
      <pitch>59</pitch>
      <offsetSec>4.6629</offsetSec>
      <excitationStyle>MU</excitationStyle>
      <expressionStyle>NO</expressionStyle>
      <fretNumber>4</fretNumber>
      <stringNumber>4</stringNumber>
      <modulationFrequency>0</modulationFrequency>
      <modulationFrequencyRange>0</modulationFrequencyRange>
    </event>
    <event>
      <onsetSec>4.6512</onsetSec>
      <pitch>52</pitch>
      <offsetSec>4.924</offsetSec>
      <excitationStyle>MU</excitationStyle>
      <expressionStyle>NO</expressionStyle>
      <fretNumber>2</fretNumber>
      <stringNumber>3</stringNumber>
      <modulationFrequency>0</modulationFrequency>
      <modulationFrequencyRange>0</modulationFrequencyRange>
    </event>
    <event>
      <onsetSec>4.9197</onsetSec>
      <pitch>64</pitch>
      <offsetSec>5.1875</offsetSec>
      <excitationStyle>MU</excitationStyle>
      <expressionStyle>NO</expressionStyle>
      <fretNumber>0</fretNumber>
      <stringNumber>6</stringNumber>
      <modulationFrequency>0</modulationFrequency>
      <modulationFrequencyRange>0</modulationFrequencyRange>
    </event>
    <event>
      <onsetSec>5.2009</onsetSec>
      <pitch>59</pitch>
      <offsetSec>5.5102</offsetSec>
      <excitationStyle>MU</excitationStyle>
      <expressionStyle>NO</expressionStyle>
      <fretNumber>0</fretNumber>
      <stringNumber>5</stringNumber>
      <modulationFrequency>0</modulationFrequency>
      <modulationFrequencyRange>0</modulationFrequencyRange>
    </event>
    <event>
      <onsetSec>5.9646</onsetSec>
      <pitch>50</pitch>
      <offsetSec>6.4424</offsetSec>
      <excitationStyle>MU</excitationStyle>
      <expressionStyle>NO</expressionStyle>
      <fretNumber>5</fretNumber>
      <stringNumber>2</stringNumber>
      <modulationFrequency>0</modulationFrequency>
      <modulationFrequencyRange>0</modulationFrequencyRange>
    </event>
    <event>
      <onsetSec>6.2168</onsetSec>
      <pitch>54</pitch>
      <offsetSec>6.4568</offsetSec>
      <excitationStyle>MU</excitationStyle>
      <expressionStyle>NO</expressionStyle>
      <fretNumber>4</fretNumber>
      <stringNumber>3</stringNumber>
      <modulationFrequency>0</modulationFrequency>
      <modulationFrequencyRange>0</modulationFrequencyRange>
    </event>
    <event>
      <onsetSec>6.449</onsetSec>
      <pitch>55</pitch>
      <offsetSec>6.6861</offsetSec>
      <excitationStyle>MU</excitationStyle>
      <expressionStyle>NO</expressionStyle>
      <fretNumber>0</fretNumber>
      <stringNumber>4</stringNumber>
      <modulationFrequency>0</modulationFrequency>
      <modulationFrequencyRange>0</modulationFrequencyRange>
    </event>
    <event>
      <onsetSec>6.683</onsetSec>
      <pitch>54</pitch>
      <offsetSec>6.982</offsetSec>
      <excitationStyle>MU</excitationStyle>
      <expressionStyle>NO</expressionStyle>
      <fretNumber>4</fretNumber>
      <stringNumber>3</stringNumber>
      <modulationFrequency>0</modulationFrequency>
      <modulationFrequencyRange>0</modulationFrequencyRange>
    </event>
    <event>
      <onsetSec>6.9605</onsetSec>
      <pitch>64</pitch>
      <offsetSec>7.1526</offsetSec>
      <excitationStyle>MU</excitationStyle>
      <expressionStyle>NO</expressionStyle>
      <fretNumber>0</fretNumber>
      <stringNumber>6</stringNumber>
      <modulationFrequency>0</modulationFrequency>
      <modulationFrequencyRange>0</modulationFrequencyRange>
    </event>
    <event>
      <onsetSec>7.2145</onsetSec>
      <pitch>59</pitch>
      <offsetSec>7.6107</offsetSec>
      <excitationStyle>MU</excitationStyle>
      <expressionStyle>NO</expressionStyle>
      <fretNumber>0</fretNumber>
      <stringNumber>5</stringNumber>
      <modulationFrequency>0</modulationFrequency>
      <modulationFrequencyRange>0</modulationFrequencyRange>
    </event>
    <event>
      <onsetSec>7.9057</onsetSec>
      <pitch>50</pitch>
      <offsetSec>8.4056</offsetSec>
      <excitationStyle>MU</excitationStyle>
      <expressionStyle>NO</expressionStyle>
      <fretNumber>5</fretNumber>
      <stringNumber>2</stringNumber>
      <modulationFrequency>0</modulationFrequency>
      <modulationFrequencyRange>0</modulationFrequencyRange>
    </event>
    <event>
      <onsetSec>8.1832</onsetSec>
      <pitch>54</pitch>
      <offsetSec>8.4282</offsetSec>
      <excitationStyle>MU</excitationStyle>
      <expressionStyle>NO</expressionStyle>
      <fretNumber>4</fretNumber>
      <stringNumber>3</stringNumber>
      <modulationFrequency>0</modulationFrequency>
      <modulationFrequencyRange>0</modulationFrequencyRange>
    </event>
    <event>
      <onsetSec>8.419</onsetSec>
      <pitch>57</pitch>
      <offsetSec>8.6684</offsetSec>
      <excitationStyle>MU</excitationStyle>
      <expressionStyle>NO</expressionStyle>
      <fretNumber>2</fretNumber>
      <stringNumber>4</stringNumber>
      <modulationFrequency>0</modulationFrequency>
      <modulationFrequencyRange>0</modulationFrequencyRange>
    </event>
    <event>
      <onsetSec>8.6621</onsetSec>
      <pitch>54</pitch>
      <offsetSec>8.9375</offsetSec>
      <excitationStyle>MU</excitationStyle>
      <expressionStyle>NO</expressionStyle>
      <fretNumber>4</fretNumber>
      <stringNumber>3</stringNumber>
      <modulationFrequency>0</modulationFrequency>
      <modulationFrequencyRange>0</modulationFrequencyRange>
    </event>
    <event>
      <onsetSec>8.9252</onsetSec>
      <pitch>64</pitch>
      <offsetSec>9.1554</offsetSec>
      <excitationStyle>MU</excitationStyle>
      <expressionStyle>NO</expressionStyle>
      <fretNumber>0</fretNumber>
      <stringNumber>6</stringNumber>
      <modulationFrequency>0</modulationFrequency>
      <modulationFrequencyRange>0</modulationFrequencyRange>
    </event>
    <event>
      <onsetSec>9.1991</onsetSec>
      <pitch>59</pitch>
      <offsetSec>9.494</offsetSec>
      <excitationStyle>MU</excitationStyle>
      <expressionStyle>NO</expressionStyle>
      <fretNumber>0</fretNumber>
      <stringNumber>5</stringNumber>
      <modulationFrequency>0</modulationFrequency>
      <modulationFrequencyRange>0</modulationFrequencyRange>
    </event>
    <event>
      <onsetSec>9.9465</onsetSec>
      <pitch>50</pitch>
      <offsetSec>10.2281</offsetSec>
      <excitationStyle>MU</excitationStyle>
      <expressionStyle>NO</expressionStyle>
      <fretNumber>5</fretNumber>
      <stringNumber>2</stringNumber>
      <modulationFrequency>0</modulationFrequency>
      <modulationFrequencyRange>0</modulationFrequencyRange>
    </event>
    <event>
      <onsetSec>9.9514</onsetSec>
      <pitch>57</pitch>
      <offsetSec>10.0937</offsetSec>
      <excitationStyle>MU</excitationStyle>
      <expressionStyle>NO</expressionStyle>
      <fretNumber>7</fretNumber>
      <stringNumber>3</stringNumber>
      <modulationFrequency>0</modulationFrequency>
      <modulationFrequencyRange>0</modulationFrequencyRange>
    </event>
    <event>
      <onsetSec>10.2313</onsetSec>
      <pitch>50</pitch>
      <offsetSec>10.5335</offsetSec>
      <excitationStyle>MU</excitationStyle>
      <expressionStyle>NO</expressionStyle>
      <fretNumber>5</fretNumber>
      <stringNumber>2</stringNumber>
      <modulationFrequency>0</modulationFrequency>
      <modulationFrequencyRange>0</modulationFrequencyRange>
    </event>
    <event>
      <onsetSec>10.2349</onsetSec>
      <pitch>57</pitch>
      <offsetSec>10.5885</offsetSec>
      <excitationStyle>MU</excitationStyle>
      <expressionStyle>NO</expressionStyle>
      <fretNumber>7</fretNumber>
      <stringNumber>3</stringNumber>
      <modulationFrequency>0</modulationFrequency>
      <modulationFrequencyRange>0</modulationFrequencyRange>
    </event>
    <event>
      <onsetSec>10.7283</onsetSec>
      <pitch>62</pitch>
      <offsetSec>10.7755</offsetSec>
      <excitationStyle>MU</excitationStyle>
      <expressionStyle>NO</expressionStyle>
      <fretNumber>7</fretNumber>
      <stringNumber>4</stringNumber>
      <modulationFrequency>0</modulationFrequency>
      <modulationFrequencyRange>0</modulationFrequencyRange>
    </event>
    <event>
      <onsetSec>10.7338</onsetSec>
      <pitch>64</pitch>
      <offsetSec>10.769</offsetSec>
      <excitationStyle>MU</excitationStyle>
      <expressionStyle>NO</expressionStyle>
      <fretNumber>5</fretNumber>
      <stringNumber>5</stringNumber>
      <modulationFrequency>0</modulationFrequency>
      <modulationFrequencyRange>0</modulationFrequencyRange>
    </event>
    <event>
      <onsetSec>10.7356</onsetSec>
      <pitch>69</pitch>
      <offsetSec>11.0802</offsetSec>
      <excitationStyle>MU</excitationStyle>
      <expressionStyle>NO</expressionStyle>
      <fretNumber>5</fretNumber>
      <stringNumber>6</stringNumber>
      <modulationFrequency>0</modulationFrequency>
      <modulationFrequencyRange>0</modulationFrequencyRange>
    </event>
    <event>
      <onsetSec>11.4939</onsetSec>
      <pitch>48</pitch>
      <offsetSec>11.7475</offsetSec>
      <excitationStyle>MU</excitationStyle>
      <expressionStyle>NO</expressionStyle>
      <fretNumber>3</fretNumber>
      <stringNumber>2</stringNumber>
      <modulationFrequency>0</modulationFrequency>
      <modulationFrequencyRange>0</modulationFrequencyRange>
    </event>
    <event>
      <onsetSec>11.4993</onsetSec>
      <pitch>55</pitch>
      <offsetSec>11.6828</offsetSec>
      <excitationStyle>MU</excitationStyle>
      <expressionStyle>NO</expressionStyle>
      <fretNumber>5</fretNumber>
      <stringNumber>3</stringNumber>
      <modulationFrequency>0</modulationFrequency>
      <modulationFrequencyRange>0</modulationFrequencyRange>
    </event>
    <event>
      <onsetSec>11.746</onsetSec>
      <pitch>48</pitch>
      <offsetSec>12.0242</offsetSec>
      <excitationStyle>MU</excitationStyle>
      <expressionStyle>NO</expressionStyle>
      <fretNumber>3</fretNumber>
      <stringNumber>2</stringNumber>
      <modulationFrequency>0</modulationFrequency>
      <modulationFrequencyRange>0</modulationFrequencyRange>
    </event>
    <event>
      <onsetSec>11.746</onsetSec>
      <pitch>55</pitch>
      <offsetSec>12.0634</offsetSec>
      <excitationStyle>MU</excitationStyle>
      <expressionStyle>NO</expressionStyle>
      <fretNumber>5</fretNumber>
      <stringNumber>3</stringNumber>
      <modulationFrequency>0</modulationFrequency>
      <modulationFrequencyRange>0</modulationFrequencyRange>
    </event>
    <event>
      <onsetSec>12.2068</onsetSec>
      <pitch>60</pitch>
      <offsetSec>12.4229</offsetSec>
      <excitationStyle>MU</excitationStyle>
      <expressionStyle>NO</expressionStyle>
      <fretNumber>5</fretNumber>
      <stringNumber>4</stringNumber>
      <modulationFrequency>0</modulationFrequency>
      <modulationFrequencyRange>0</modulationFrequencyRange>
    </event>
    <event>
      <onsetSec>12.2104</onsetSec>
      <pitch>62</pitch>
      <offsetSec>12.4121</offsetSec>
      <excitationStyle>MU</excitationStyle>
      <expressionStyle>NO</expressionStyle>
      <fretNumber>3</fretNumber>
      <stringNumber>5</stringNumber>
      <modulationFrequency>0</modulationFrequency>
      <modulationFrequencyRange>0</modulationFrequencyRange>
    </event>
    <event>
      <onsetSec>12.2141</onsetSec>
      <pitch>67</pitch>
      <offsetSec>12.412</offsetSec>
      <excitationStyle>MU</excitationStyle>
      <expressionStyle>NO</expressionStyle>
      <fretNumber>3</fretNumber>
      <stringNumber>6</stringNumber>
      <modulationFrequency>0</modulationFrequency>
      <modulationFrequencyRange>0</modulationFrequencyRange>
    </event>
    <event>
      <onsetSec>12.9524</onsetSec>
      <pitch>43</pitch>
      <offsetSec>13.3287</offsetSec>
      <excitationStyle>MU</excitationStyle>
      <expressionStyle>NO</expressionStyle>
      <fretNumber>3</fretNumber>
      <stringNumber>1</stringNumber>
      <modulationFrequency>0</modulationFrequency>
      <modulationFrequencyRange>0</modulationFrequencyRange>
    </event>
    <event>
      <onsetSec>12.9578</onsetSec>
      <pitch>50</pitch>
      <offsetSec>13.4194</offsetSec>
      <excitationStyle>MU</excitationStyle>
      <expressionStyle>NO</expressionStyle>
      <fretNumber>5</fretNumber>
      <stringNumber>2</stringNumber>
      <modulationFrequency>0</modulationFrequency>
      <modulationFrequencyRange>0</modulationFrequencyRange>
    </event>
    <event>
      <onsetSec>13.4585</onsetSec>
      <pitch>45</pitch>
      <offsetSec>13.7949</offsetSec>
      <excitationStyle>MU</excitationStyle>
      <expressionStyle>NO</expressionStyle>
      <fretNumber>5</fretNumber>
      <stringNumber>1</stringNumber>
      <modulationFrequency>0</modulationFrequency>
      <modulationFrequencyRange>0</modulationFrequencyRange>
    </event>
    <event>
      <onsetSec>13.4621</onsetSec>
      <pitch>52</pitch>
      <offsetSec>13.8462</offsetSec>
      <excitationStyle>MU</excitationStyle>
      <expressionStyle>NO</expressionStyle>
      <fretNumber>7</fretNumber>
      <stringNumber>2</stringNumber>
      <modulationFrequency>0</modulationFrequency>
      <modulationFrequencyRange>0</modulationFrequencyRange>
    </event>
    <event>
      <onsetSec>13.9302</onsetSec>
      <pitch>45</pitch>
      <offsetSec>15.9501</offsetSec>
      <excitationStyle>MU</excitationStyle>
      <expressionStyle>NO</expressionStyle>
      <fretNumber>5</fretNumber>
      <stringNumber>1</stringNumber>
      <modulationFrequency>0</modulationFrequency>
      <modulationFrequencyRange>0</modulationFrequencyRange>
    </event>
    <event>
      <onsetSec>13.9374</onsetSec>
      <pitch>52</pitch>
      <offsetSec>15.5402</offsetSec>
      <excitationStyle>MU</excitationStyle>
      <expressionStyle>NO</expressionStyle>
      <fretNumber>7</fretNumber>
      <stringNumber>2</stringNumber>
      <modulationFrequency>0</modulationFrequency>
      <modulationFrequencyRange>0</modulationFrequencyRange>
    </event>
  </transcription>
</instrumentRecording> 
