<?xml version="1.0" encoding="UTF-8" standalone="yes"?>
<instrumentRecording>
  <globalParameter>
    <audioFileName>\FS_Lick3_MSBDN.wav</audioFileName>
    <instrument>EGUI</instrument>
    <instrumentModel>Fender Stratocaster</instrumentModel>
    <pickUpSetting>unknown</pickUpSetting>
    <instrumentTuning>40  45  50  55  59  64</instrumentTuning>
    <recordingDate>13-02-14</recordingDate>
    <recordingArtist>Christian Kehling</recordingArtist>
    <instrumentBodyMaterial>unknown</instrumentBodyMaterial>
    <instrumentStringMaterial>Steel</instrumentStringMaterial>
    <composer>Christian Kehling</composer>
  </globalParameter>
  <transcription>
    <event>
      <onsetSec>1.4349</onsetSec>
      <pitch>48</pitch>
      <offsetSec>1.6417</offsetSec>
      <excitationStyle>MU</excitationStyle>
      <expressionStyle>NO</expressionStyle>
      <fretNumber>3</fretNumber>
      <stringNumber>2</stringNumber>
      <modulationFrequency>0</modulationFrequency>
      <modulationFrequencyRange>0</modulationFrequencyRange>
    </event>
    <event>
      <onsetSec>1.6203</onsetSec>
      <pitch>49</pitch>
      <offsetSec>1.7617</offsetSec>
      <excitationStyle>MU</excitationStyle>
      <expressionStyle>NO</expressionStyle>
      <fretNumber>4</fretNumber>
      <stringNumber>2</stringNumber>
      <modulationFrequency>0</modulationFrequency>
      <modulationFrequencyRange>0</modulationFrequencyRange>
    </event>
    <event>
      <onsetSec>1.7689</onsetSec>
      <pitch>50</pitch>
      <offsetSec>1.9563</offsetSec>
      <excitationStyle>MU</excitationStyle>
      <expressionStyle>NO</expressionStyle>
      <fretNumber>5</fretNumber>
      <stringNumber>2</stringNumber>
      <modulationFrequency>0</modulationFrequency>
      <modulationFrequencyRange>0</modulationFrequencyRange>
    </event>
    <event>
      <onsetSec>1.9467</onsetSec>
      <pitch>53</pitch>
      <offsetSec>2.2622</offsetSec>
      <excitationStyle>MU</excitationStyle>
      <expressionStyle>NO</expressionStyle>
      <fretNumber>3</fretNumber>
      <stringNumber>3</stringNumber>
      <modulationFrequency>0</modulationFrequency>
      <modulationFrequencyRange>0</modulationFrequencyRange>
    </event>
    <event>
      <onsetSec>2.2603</onsetSec>
      <pitch>50</pitch>
      <offsetSec>2.4333</offsetSec>
      <excitationStyle>MU</excitationStyle>
      <expressionStyle>NO</expressionStyle>
      <fretNumber>5</fretNumber>
      <stringNumber>2</stringNumber>
      <modulationFrequency>0</modulationFrequency>
      <modulationFrequencyRange>0</modulationFrequencyRange>
    </event>
    <event>
      <onsetSec>2.4489</onsetSec>
      <pitch>48</pitch>
      <offsetSec>2.5728</offsetSec>
      <excitationStyle>MU</excitationStyle>
      <expressionStyle>DN</expressionStyle>
      <fretNumber>3</fretNumber>
      <stringNumber>2</stringNumber>
      <modulationFrequency>0</modulationFrequency>
      <modulationFrequencyRange>0</modulationFrequencyRange>
    </event>
    <event>
      <onsetSec>2.7797</onsetSec>
      <pitch>50</pitch>
      <offsetSec>3.1998</offsetSec>
      <excitationStyle>MU</excitationStyle>
      <expressionStyle>NO</expressionStyle>
      <fretNumber>5</fretNumber>
      <stringNumber>2</stringNumber>
      <modulationFrequency>0</modulationFrequency>
      <modulationFrequencyRange>0</modulationFrequencyRange>
    </event>
    <event>
      <onsetSec>3.2819</onsetSec>
      <pitch>55</pitch>
      <offsetSec>3.7466</offsetSec>
      <excitationStyle>MU</excitationStyle>
      <expressionStyle>SL</expressionStyle>
      <fretNumber>5</fretNumber>
      <stringNumber>3</stringNumber>
      <modulationFrequency>1.0761</modulationFrequency>
      <modulationFrequencyRange>200</modulationFrequencyRange>
    </event>
    <event>
      <onsetSec>3.7517</onsetSec>
      <pitch>55</pitch>
      <offsetSec>3.961</offsetSec>
      <excitationStyle>MU</excitationStyle>
      <expressionStyle>NO</expressionStyle>
      <fretNumber>5</fretNumber>
      <stringNumber>3</stringNumber>
      <modulationFrequency>0</modulationFrequency>
      <modulationFrequencyRange>0</modulationFrequencyRange>
    </event>
    <event>
      <onsetSec>3.9721</onsetSec>
      <pitch>52</pitch>
      <offsetSec>4.2799</offsetSec>
      <excitationStyle>MU</excitationStyle>
      <expressionStyle>BE</expressionStyle>
      <fretNumber>7</fretNumber>
      <stringNumber>2</stringNumber>
      <modulationFrequency>0</modulationFrequency>
      <modulationFrequencyRange>0</modulationFrequencyRange>
    </event>
    <event>
      <onsetSec>4.2781</onsetSec>
      <pitch>45</pitch>
      <offsetSec>4.4619</offsetSec>
      <excitationStyle>MU</excitationStyle>
      <expressionStyle>NO</expressionStyle>
      <fretNumber>0</fretNumber>
      <stringNumber>2</stringNumber>
      <modulationFrequency>0</modulationFrequency>
      <modulationFrequencyRange>0</modulationFrequencyRange>
    </event>
    <event>
      <onsetSec>4.4616</onsetSec>
      <pitch>48</pitch>
      <offsetSec>4.7766</offsetSec>
      <excitationStyle>MU</excitationStyle>
      <expressionStyle>NO</expressionStyle>
      <fretNumber>3</fretNumber>
      <stringNumber>2</stringNumber>
      <modulationFrequency>0</modulationFrequency>
      <modulationFrequencyRange>0</modulationFrequencyRange>
    </event>
    <event>
      <onsetSec>4.7549</onsetSec>
      <pitch>50</pitch>
      <offsetSec>5.4233</offsetSec>
      <excitationStyle>MU</excitationStyle>
      <expressionStyle>NO</expressionStyle>
      <fretNumber>5</fretNumber>
      <stringNumber>2</stringNumber>
      <modulationFrequency>0</modulationFrequency>
      <modulationFrequencyRange>0</modulationFrequencyRange>
    </event>
  </transcription>
</instrumentRecording> 
